constclust/__init__.py
constclust/_version.py
constclust/aggregate.py
constclust/cluster.py
constclust/clustree.py
constclust/paramspace.py
constclust/permute.py
constclust/plotting.py
constclust/utils.py
constclust-0.2.0.dist-info/LICENSE
constclust-0.2.0.dist-info/METADATA
constclust-0.2.0.dist-info/WHEEL
constclust-0.2.0.dist-info/top_level.txt
constclust-0.2.0.dist-info/RECORD
