Metadata-Version: 2.1
Name: constclust
Version: 0.2.0
Summary: UNKNOWN
Home-page: https://github.com/ivirshup/ConsistentClusters
Author: Isaac Virshup
Author-email: ivirshup@gmail.com
License: UNKNOWN
Platform: UNKNOWN
Requires-Python: >=3.7
Requires-Dist: scanpy (>=1.4)
Requires-Dist: numba (>=0.42.1)
Requires-Dist: pandas (>=0.24.1)
Requires-Dist: scikit-learn
Requires-Dist: numpy
Requires-Dist: scipy
Requires-Dist: python-igraph
Requires-Dist: matplotlib
Requires-Dist: seaborn
Requires-Dist: leidenalg
Requires-Dist: tqdm
Requires-Dist: bokeh
Requires-Dist: datashader
Requires-Dist: pygraphviz
Requires-Dist: sphinx-autodoc-typehints
Requires-Dist: scanpydoc
Requires-Dist: sphinx-rtd-theme
Provides-Extra: dev
Requires-Dist: pytest ; extra == 'dev'
Requires-Dist: scanpydoc ; extra == 'dev'
Requires-Dist: sphinx ; extra == 'dev'
